LICENSE.txt
README.md
setup.cfg
setup.py
dist/pygamentos-0.2.9.tar.gz
dist/pypayments-0.2.9.tar.gz
docs/README.rst
docs/index.rst
pygamentos/__init__.py
pygamentos/cancel_payment.py
pygamentos/config.py
pygamentos/information_payment.py
pygamentos/request_payment.py
pygamentos/request_refund.py
pygamentos.egg-info/PKG-INFO
pygamentos.egg-info/SOURCES.txt
pygamentos.egg-info/dependency_links.txt
pygamentos.egg-info/top_level.txt
pygamentos/__pycache__/__init__.cpython-36.pyc
pygamentos/__pycache__/cancel_payment.cpython-36.pyc
pygamentos/__pycache__/config.cpython-36.pyc
pygamentos/__pycache__/information_payment.cpython-36.pyc
pygamentos/__pycache__/request_payment.cpython-36.pyc
pygamentos/__pycache__/request_refund.cpython-36.pyc