Metadata-Version: 1.0
Name: pygamentos
Version: 0.3.0
Summary: Unofficial library for make payments in Python
Home-page: https://github.com/hubtec/pygamentos
Author: Daniel Guilhermino
Author-email: daniel@hubtec.com.br
License: MIT
Keywords: ebanx,payments,gateway,pagamentos,PicPay
Platform: UNKNOWN
